metagen/__init__.py
metagen/__main__.py
metagen/metagenerator.py
metagen/test_cli
metagen/version.py
metagen/tests/__init__.py
metagen/tests/test_meta.py
metagen-0.7.4.dist-info/METADATA
metagen-0.7.4.dist-info/WHEEL
metagen-0.7.4.dist-info/entry_points.txt
metagen-0.7.4.dist-info/top_level.txt
metagen-0.7.4.dist-info/RECORD
