Metadata-Version: 2.1
Name: metagen
Version: 0.7.4
Summary: Metadata.xml Generator for Ebuilds
Author-email: Rob Cakebread <pythonhead@gentoo.org>, Jesus Rivero <neurogeek@gentoo.org>, Sebastian Pipping <sebastian@pipping.org>
License: GPL-2
Project-URL: Git repository, https://gitweb.gentoo.org/proj/metagen.git/
Project-URL: Issue tracker, https://bugs.gentoo.org/
Project-URL: Change log, https://gitweb.gentoo.org/proj/metagen.git/plain/docs/ChangeLog
Classifier: Development Status :: 5 - Production/Stable
Classifier: Environment :: Console
Classifier: Intended Audience :: Developers
Classifier: License :: OSI Approved :: GNU General Public License v2 (GPLv2)
Classifier: Natural Language :: English
Classifier: Programming Language :: Python
Classifier: Programming Language :: Python :: 3
Classifier: Programming Language :: Python :: 3.7
Classifier: Programming Language :: Python :: 3.8
Classifier: Programming Language :: Python :: 3.9
Classifier: Programming Language :: Python :: 3.10
Classifier: Programming Language :: Python :: 3 :: Only
Classifier: Topic :: Software Development
Classifier: Topic :: Text Processing :: Markup :: XML
Classifier: Topic :: Utilities
Requires-Dist: lxml
